napari_lazy_openslide/__init__.py
napari_lazy_openslide/_version.py
napari_lazy_openslide/lazy_openslide.py
napari_lazy_openslide/store.py
napari_lazy_openslide/_tests/__init__.py
napari_lazy_openslide/_tests/test_lazy_openslide.py
napari_lazy_openslide-0.3.0.dist-info/LICENSE
napari_lazy_openslide-0.3.0.dist-info/METADATA
napari_lazy_openslide-0.3.0.dist-info/WHEEL
napari_lazy_openslide-0.3.0.dist-info/entry_points.txt
napari_lazy_openslide-0.3.0.dist-info/top_level.txt
napari_lazy_openslide-0.3.0.dist-info/RECORD
