Metadata-Version: 2.1
Name: napari-lazy-openslide
Version: 0.3.0
Summary: A plugin to lazily load multiscale whole-slide images with openslide and dask
Home-page: https://github.com/manzt/napari-lazy-openslide
Author: Trevor Manz
Author-email: trevor.j.manz@gmail.com
License: BSD-3
Classifier: Development Status :: 4 - Beta
Classifier: Intended Audience :: Developers
Classifier: Topic :: Software Development :: Testing
Classifier: Programming Language :: Python
Classifier: Programming Language :: Python :: 3.7
Classifier: Programming Language :: Python :: 3.8
Classifier: Programming Language :: Python :: 3.9
Classifier: Operating System :: OS Independent
Classifier: License :: OSI Approved :: BSD License
Classifier: Framework :: napari
Requires-Python: >=3.6
License-File: LICENSE
Requires-Dist: napari-plugin-engine (>=0.1.4)
Requires-Dist: zarr (>=2.11.0)
Requires-Dist: numpy
Requires-Dist: dask[array]
Requires-Dist: openslide-python
